envedseted/__init__.py
envedseted/cli.py
envedseted/path_utils.py
envedseted-0.2.0.dist-info/License
envedseted-0.2.0.dist-info/METADATA
envedseted-0.2.0.dist-info/WHEEL
envedseted-0.2.0.dist-info/entry_points.txt
envedseted-0.2.0.dist-info/top_level.txt
envedseted-0.2.0.dist-info/RECORD
