Metadata-Version: 2.2
Name: envedseted
Version: 0.2.0
Summary: Advanced environment variable manager with PATH support
Home-page: https://github.com/ThanaphatSuporn/envedseted
Author: Catergems
Author-email: supornthanaphat@gmail.com
Classifier: Programming Language :: Python :: 3
Classifier: Operating System :: OS Independent
Classifier: License :: OSI Approved :: MIT License
Requires-Python: >=3.7
License-File: License
Dynamic: author
Dynamic: author-email
Dynamic: classifier
Dynamic: description
Dynamic: description-content-type
Dynamic: home-page
Dynamic: requires-python
Dynamic: summary
